{
    "wiki": {
        "url": "https://blueoath.miraheze.org/wiki/Koln",
        "active": false
    },
    "on_sheet": true,
    "en": "Koln",
    "jp": "\u30b1\u30eb\u30f3",
    "dname": "K\u00f6ln",
    "rarity": "R",
    "prefix": "KMS",
    "faction": "German",
    "faction_jp": "\u83b1\u8335",
    "hull_code": "CL",
    "ship_class": "Light Cruiser",
    "stats": {},
    "lb": [],
    "traits": [
        {
            "name": "Craftswoman",
            "text": null
        },
        {
            "name": "Scrap",
            "text": null
        }
    ],
    "skills": [
        {
            "name": "Special Torpedoes (\u7279\u6b8a\u9b5a\u96f7)",
            "text": "1. When entering a battle, gains 1 [Torpedo Salvo] charge, 40% chance to gain a further 1 [Torpedo Salvo] charge."
        },
        {
            "name": "Ammunition Delivery (\u5f3e\u85ac\u8f38\u9001)",
            "text": "1. When battle starts, increase Flagship's [Main Battery] damage by 20%."
        }
    ],
    "img_sq": "https://static.miraheze.org/blueoathwiki/f/f7/Koln_Portrait_Square.png",
    "img_rec": null,
    "gallery": [],
    "acquisition": null,
    "comment": null,
    "VA": null
}